hillmaker/__init__.py
hillmaker/bydatetime.py
hillmaker/console.py
hillmaker/hills.py
hillmaker/hmlib.py
hillmaker/legacy.py
hillmaker/plotting.py
hillmaker/scenario.py
hillmaker/summarize.py
hillmaker/utils.py
hillmaker-0.8.1.dist-info/AUTHORS
hillmaker-0.8.1.dist-info/LICENSE
hillmaker-0.8.1.dist-info/METADATA
hillmaker-0.8.1.dist-info/WHEEL
hillmaker-0.8.1.dist-info/entry_points.txt
hillmaker-0.8.1.dist-info/top_level.txt
hillmaker-0.8.1.dist-info/RECORD
