Metadata-Version: 2.1
Name: hillmaker
Version: 0.8.1
Summary: Occupancy analysis tool for systems having time of day and day of week effects
Home-page: http://github.com/misken/hillmaker/
Author: Mark Isken
Author-email: isken@oakland.edu
Project-URL: Source, http://github.com/misken/hillmaker
Project-URL: Examples, https://github.com/misken/hillmaker-examples
Platform: any
Classifier: Programming Language :: Python :: 3 
Classifier: Programming Language :: Python :: 3.10 
Classifier: Development Status :: 4 - Beta
Classifier: Natural Language :: English
Classifier: Environment :: Console
Classifier: Intended Audience :: Science/Research
Classifier: Intended Audience :: Healthcare Industry
Classifier: License :: OSI Approved
Classifier: Operating System :: OS Independent
Classifier: Topic :: Scientific/Engineering :: Information Analysis
License-File: LICENSE
License-File: AUTHORS
Requires-Dist: pandas >=2.0.0
Requires-Dist: numpy >=1.22
Requires-Dist: tomli >=2.0.1
Requires-Dist: matplotlib >=3.7.1
Requires-Dist: pydantic >=2.1.1
Requires-Dist: seaborn >=0.12.2
Requires-Dist: Jinja2
Requires-Dist: ipykernel
